{
  "id": "4kzin-dist",
  "name": "4Kzin Distribution",
  "version": "1.0.0",
  "servers": [
    {
      "id": "4kzin-server",
      "name": "Servidor 4Kzin",
      "description": "Servidor oficial do 4Kzin Launcher!",
      "address": "26.193.254.44",
      "port": 25565,
      "default": true
    }
  ],
  "instances": [
    {
      "id": "4kzin-modpack",
      "name": "4Kzin Modpack",
      "version": "1.0.0",
      "minecraftVersion": "1.12.2",
      "server": "4kzin-server",
      "description": "Modpack oficial do 4Kzin com tudo pronto pra jogar!",
      "releaseTime": "2025-10-21T00:00:00Z",
      "type": "custom",
      "mainClass": "net.minecraft.launchwrapper.Launch",
      "assets": "legacy",
      "libraries": [],
      "files": [
        {
          "path": "4kzin_modpack.zip",
          "url": "https://seusite.com/4kzin_modpack.zip",
          "hash": "sha1:PLACEHOLDER_HASH_AQUI"
        }
      ],
      "javaVersion": 8,
      "mainServer": "4kzin-server"
    }
  ],
  "defaultInstanceId": "4kzin-modpack",
  "defaultServerId": "4kzin-server"
}
